strmbrkr/__init__.py
strmbrkr/config.py
strmbrkr/job.py
strmbrkr/logging.py
strmbrkr/producer.py
strmbrkr/worker.py
strmbrkr/endpoints/__init__.py
strmbrkr/endpoints/base.py
strmbrkr/endpoints/ipc_proto.py
strmbrkr/endpoints/tcp_proto.py
strmbrkr/key_value_store/__init__.py
strmbrkr/key_value_store/append_transaction.py
strmbrkr/key_value_store/cache_transactions.py
strmbrkr/key_value_store/dump_transaction.py
strmbrkr/key_value_store/flush_transaction.py
strmbrkr/key_value_store/get_transaction.py
strmbrkr/key_value_store/job_status_transaction.py
strmbrkr/key_value_store/key_value_store.py
strmbrkr/key_value_store/ping_transaction.py
strmbrkr/key_value_store/pop_transaction.py
strmbrkr/key_value_store/set_transaction.py
strmbrkr/key_value_store/shutdown_transaction.py
strmbrkr/key_value_store/transaction.py
strmbrkr-1.4.1.dist-info/LICENSE
strmbrkr-1.4.1.dist-info/METADATA
strmbrkr-1.4.1.dist-info/WHEEL
strmbrkr-1.4.1.dist-info/top_level.txt
strmbrkr-1.4.1.dist-info/RECORD
