Metadata-Version: 2.1
Name: strmbrkr
Version: 1.4.1
Summary: Simultaneous Task Registrar and Message Broker
Requires-Python: >=3.7
License-File: LICENSE
Requires-Dist: pyzmq
Provides-Extra: test
Requires-Dist: pytest; extra == "test"
Requires-Dist: coverage; extra == "test"
